openengine/__init__.py
openengine/main.py
openengine/data/__init__.py
openengine/data/yahoo_connector.py
openengine/engine/__init__.py
openengine/engine/backtester.py
openengine/engine/live_trader.py
openengine/execution/__init__.py
openengine/execution/broker_interface.py
openengine/execution/order_manager.py
openengine/strategies/__init__.py
openengine/strategies/base_strategy.py
openengine/strategies/sample_strategy.py
openengine/utilities/__init__.py
openengine/utilities/config.py
openengine/utilities/logger.py
openengine-1.0.0.dist-info/LICENSE
openengine-1.0.0.dist-info/METADATA
openengine-1.0.0.dist-info/WHEEL
openengine-1.0.0.dist-info/entry_points.txt
openengine-1.0.0.dist-info/top_level.txt
openengine-1.0.0.dist-info/RECORD
